script2package/__init__.py
script2package/__main__.py
script2package/cli.py
script2package/util.py
script2package-1.1.0.dist-info/DESCRIPTION.rst
script2package-1.1.0.dist-info/METADATA
script2package-1.1.0.dist-info/RECORD
script2package-1.1.0.dist-info/WHEEL
script2package-1.1.0.dist-info/entry_points.txt
script2package-1.1.0.dist-info/metadata.json
script2package-1.1.0.dist-info/top_level.txt
